cut_finder.cp37-win_amd64.pyd
ExKMC/Tree.py
ExKMC/__init__.py
ExKMC/splitters/__init__.py
ExKMC/splitters/py_cut_finder.py
ExKMC/splitters/setup.py
ExKMC-0.0.3.dist-info/LICENSE
ExKMC-0.0.3.dist-info/METADATA
ExKMC-0.0.3.dist-info/WHEEL
ExKMC-0.0.3.dist-info/top_level.txt
ExKMC-0.0.3.dist-info/RECORD
