Metadata-Version: 2.1
Name: ExKMC
Version: 0.0.3
Summary: Expanding Explainable K-Means Clustering
Home-page: https://github.com/navefr/ExKMC
Author: Nave Frost
Author-email: navefrost@mail.tau.edu
License: UNKNOWN
Platform: UNKNOWN
Classifier: Programming Language :: Python :: 3
Classifier: License :: OSI Approved :: MIT License
Classifier: Operating System :: OS Independent
Requires-Python: >=3.0
